MANIFEST.in
README
README.rst
setup.py
bin/wtftz
wtftz/__init__.py
wtftz/_version.py
wtftz/converter.py
wtftz/parser.py
wtftz/timezones.py
wtftz.egg-info/PKG-INFO
wtftz.egg-info/SOURCES.txt
wtftz.egg-info/dependency_links.txt
wtftz.egg-info/requires.txt
wtftz.egg-info/top_level.txt