Metadata-Version: 1.1
Name: wtftz
Version: 0.2.4
Summary: Convert a timestamp from one timezone to another
Home-page: https://github.com/sbuss/wtftz
Author: Steven Buss
Author-email: steven.buss@gmail.com
License: UNKNOWN
Download-URL: https://github.com/sbuss/wtftz/tarball/v0.2.4
Platform: UNKNOWN
Classifier: Development Status :: 3 - Alpha
Classifier: Intended Audience :: Developers
Classifier: License :: OSI Approved :: BSD License
Classifier: Operating System :: OS Independent
Classifier: Programming Language :: Python :: 2.7
